{
	"Id" : "2991",
	"num_pc_L" : 1,
	"LA" : 0,
	"LM" : 1,
	"LD" : 0,
	"Files" : 1,
	"pcSET_L": ["365cde8"],
	"ONL_L" : "No",
	"BIC_L" : "Yes" ,
	"BICinpcSET_L" : "No",
	"idBIC_L" : "",
	"num_pc_T" : 2,
	"pcSET_T": ["0727782","24bc422"],
	"newLines_T" : "No",
	"BIC_T" : "Yes" ,
	"BICinpcSET_T" : "Yes",
	"idBIC_T" : ["0727782","24bc422"],
	"Match": ["" ],
	"ReportDate": "05/May/2013-00:45-GTM+2",
	"ClosedDate": "06/May/2013-10:25-GTM+2",
	"TTD_optimist": "13/Mar/2013-14:40-GTM+1",
	"TTD_pesisimst": "13/Mar/2013-14:40-GTM+1",
	"ToM": 54,
	"RealTTD": "18/Jan/2013-12:00-GTM+1",
	"TTN": 107,
	"TTN_p": 53,
	"TTN_o": 53,
	"Develop_Experience": "1182-08/02/2010(kimchy@gmail.com)",
	"EuB": 1075,
	"REALBIC": "7397007e05ed361805ecc3c2752e1472062c918f",
	"FTB?":"No",
	"TTF": 1,
	"IDA?": 0,
	"Reporter": "10/05/2012(simonw@apache.org)",
	"Fixer": "10/05/2012(simonw@apache.org)",
	"SPFN":"Yes",
	"SPFNC": "No",
	"SPNC": "No",
	"SPCF": "No",
	"Active": "Yes"
}