{
	"Id" : "5948",
	"num_pc_L" : 3,
	"LA" : 2,
	"LM" : 5,
	"LD" : 0,
	"Files" : 1,
	"pcSET_L": ["b35ca1a","f16eb7a","d4f0323"],
	"ONL_L" : "No",
	"BIC_L" : "Yes" ,
	"BICinpcSET_L" : "Yes",
	"idBIC_L" : ["b35ca1a"],
	"num_pc_T" : 2,
	"pcSET_T": ["b51610b","21e8669"],
	"newLines_T" : "No",
	"BIC_T" : "Yes" ,
	"BICinpcSET_T" : "Yes",
	"idBIC_T" : ["b51610b","21e8669"],
	"Match": ["b35ca1a-b51610b","f16eb7a-21e8669" ],
	"ReportDate": "26/Apr/2014-16:30-GTM+2",
	"ClosedDate": "26/Apr/2014-16:49-GTM+2",
	"TTD_optimist": "14/Jan/2014-04:00-GTM+1",
	"TTD_pesisimst": "30/Oct/2013-16:08-GTM+1",
	"ToM": "0",
	"RealTTD": "14/Jan/2014-04:00-GTM+1",
	"TTN": 102,
	"TTN_p": 179,
	"TTN_o": 102,
	"Develop_Experience": "649-16/07/2012(andrew@raines.me)",
	"EuB":  547,
	"oEuB":  547,
	"FTB?":"No",
	"TTF": 0,
	"IDA?": 0,
	"Reporter": "15/07/2013(cavannaluca@gmail.com)",
	"Fixer": "15/07/2013(cavannaluca@gmail.com)",
	"SPFN":"Yes",
	"SPFNC": "No",
	"SPNC": "No",
	"SPCF": "No",
	"Active": "Yes"
}