{
    "Title" : "STUDENT PAPER: Comparative Study of Fault-Proneness Filtering with PMD",
    "Id" : 291,
    "Date" : 2008,
    "Published" : "International Symposium on Software Reliability Engineering",
    "Authors": {
        "Name": ["Hideaki Hata"],
        "Name2": ["Osamu Mizuno"],
        "Name3": ["Tohru Kikuno"],
        "Country":["Japan"]
        },
    "Type_paper" : "Student competition (2)",
    "Project" :{ 
        "Name": ["BIRT plug-in"], 
        "Dates":["01/01/2008 - 01/31/2008"],
        },
    "Volume_data":{
        "Metric": ["#faultymodules","#nofaulty"],
        "Size":[587, 1023]
        },
    "Versioning":["CVS"],
    "Language_used":["Java"],
    "Improved_SZZ": "Yes",
    "TTV_SZZ": "No",
    "Purpose":"Fault-Proneness ",
    "Elements_risk_assessment":" ",
    "EaseOf_Reproducibility":"No",
    "Design":"quantitative&qualitative",
    "Collection": [""],
    "UseOF-SZZ": "The faulty and not-faulty modules are extracted from CVS repository using the SZZ",
    "Summary": " comparative study of Fault-proneness filtering with PMD.",
    "Outcome": " The result of experiment showed that the Fault-proneness filtering obtains higher F1(used to combine recall and precision)"
}